AntPool/AntPool.py
AntPool/__init__.py
AntPool/antpoolClient.py
AntPool/antpoolSrv.py
AntPool-0.12.dist-info/LICENSE
AntPool-0.12.dist-info/METADATA
AntPool-0.12.dist-info/WHEEL
AntPool-0.12.dist-info/entry_points.txt
AntPool-0.12.dist-info/top_level.txt
AntPool-0.12.dist-info/RECORD
