Metadata-Version: 2.1
Name: AntPool
Version: 0.12
Summary: AntPool
Home-page: https://github.com/wolf71/AntPool
Author: Charles Lai
Author-email: 
License: UNKNOWN
Platform: UNKNOWN
Classifier: Programming Language :: Python :: 3
Classifier: License :: OSI Approved :: MIT License
Classifier: Operating System :: OS Independent
License-File: LICENSE
Requires-Dist: tornado (==6.1.0)
